
[
  {
    "title": "mental health resources",
    "url": "https://curative.com/mental-health",
    "topic": [
      "mental-health"
    ]
  },
  {
    "title": "Curative Drug Search",
    "url": "https://curative.com/drugs",
    "topic": [
      "medications"
    ]
  },
  {
    "title": "Curative Telehealth",
    "url": "https://curative.com/telehealth",
    "topic": [
      "telehealth"
    ]
  },
  {
    "title": "Curative Cash Card frequently asked questions",
    "url": "https://curative.com/faq/cash-card",
    "topic": [
      "cash-card"
    ]
  },
  {
    "title": "How the Curative Cash Card Stands Out from HSA and FSA for Affordable Health Insurance Optimization",
    "url": "https://curative.com/blog/how-the-curative-cash-card-stands-out-from-hsa-and-fsa-for-affordable-health",
    "topic": [
      "cash-card"
    ]
  }
]
